{
  "date": "2026-02-04",
  "timestamp": "2026-02-04T14:04:00+08:00",
  "actions": [
    {
      "code": "600988",
      "name": "赤峰黄金",
      "action": "HOLD",
      "price": 38.37,
      "entryPrice": 39.78,
      "pnl_pct": -3.54,
      "stopLoss": 36.00,
      "targetPrice": 47.00,
      "note": "金价跳水带动股价回调，未触及止损，thesis有效"
    },
    {
      "code": "688002",
      "name": "睿创微纳",
      "action": "HOLD",
      "price": 115.39,
      "entryPrice": 114.65,
      "pnl_pct": 0.65,
      "stopLoss": 103.00,
      "targetPrice": 135.00,
      "note": "小幅盈利，thesis有效，持续持有"
    }
  ],
  "newPositions": [],
  "closedPositions": [],
  "portfolioStats": {
    "totalPositions": 2,
    "avgPnl": -1.45,
    "winners": 1,
    "losers": 1,
    "totalValue": null
  },
  "marketContext": {
    "shanghai": "+0.17%",
    "shenzhen": "-0.83%",
    "chinext": "-1.74%",
    "sentiment": "neutral",
    "hotSectors": ["煤炭行业", "酿酒行业", "船舶制造", "航空运输"],
    "notes": "市场分化明显，上证小涨但创业板大跌。煤炭板块因印尼减产大涨+4.77%，科技股普遍调整"
  },
  "watchlistNotes": "今日watchlist无BUY推荐，5只WATCH、3只AVOID。多只股票RPS120已超92%理想区间，不宜追高，继续观望"
}
